[
    { "_id": "A101", "title": "Propulsion Assignment", "course": "RS101", "notAvailableUntil": "2023-05-06", "dueDate": "2023-05-13" },
    { "_id": "A102", "title": "Combustion Analysis", "course": "RS101", "notAvailableUntil": "2023-05-13", "dueDate": "2023-05-20" },
    { "_id": "A103", "title": "Nozzle Design Project", "course": "RS101", "notAvailableUntil": "2023-05-20", "dueDate": "2023-05-27" },
    { "_id": "A201", "title": "Aerodynamics Quiz", "course": "RS102", "notAvailableUntil": "2023-06-01", "dueDate": "2023-06-08" },
    { "_id": "A202", "title": "Flow Analysis", "course": "RS102", "notAvailableUntil": "2023-06-08", "dueDate": "2023-06-15" },
    { "_id": "A203", "title": "Heating Analysis", "course": "RS102", "notAvailableUntil": "2023-06-15", "dueDate": "2023-06-22" },
    { "_id": "A301", "title": "Structural Design Task", "course": "RS103", "notAvailableUntil": "2023-07-01", "dueDate": "2023-07-08" },
    { "_id": "A302", "title": "Orbital Calculations", "course": "RS103", "notAvailableUntil": "2023-07-08", "dueDate": "2023-07-15" },
    { "_id": "A303", "title": "Systems Engineering Exam", "course": "RS103", "notAvailableUntil": "2023-07-15", "dueDate": "2023-07-22" }
  ]